faiss_imputer/__init__.py
faiss_imputer/faiss_imputer.py
faiss_imputer-0.1.1.dist-info/LICENSE
faiss_imputer-0.1.1.dist-info/METADATA
faiss_imputer-0.1.1.dist-info/WHEEL
faiss_imputer-0.1.1.dist-info/top_level.txt
faiss_imputer-0.1.1.dist-info/RECORD
