Metadata-Version: 2.1
Name: faiss-imputer
Version: 0.1.1
Summary: Impute missing values using faiss
Home-page: https://github.com/ScionKim/FaissImputer
Author: Hakkil Kim
Author-email: scionkim@gmail.com
License: MIT
License-File: LICENSE
Requires-Dist: numpy
Requires-Dist: faiss-cpu
Requires-Dist: scikit-learn
